{"project_id": "5101a1341a320ea77f000001", "discussion": {"follower_ids": [], "zooniverse_id": "DSW000057v", "user_id": "518a6f7dcaaa1f295700000b", "title": "ASW0004p3c", "users_count": 5, "created_at": "2013-06-10T18:44:26Z", "focus": {"base_type": "Subject", "_id": "ASW0004p3c", "type": "SpacewarpSubject", "name": "ASW0004p3c", "location": {"thumbnail": "http://spacewarps.org/subjects/thumbnail/5183f151e4bb210219035808.png", "standard": "http://spacewarps.org/subjects/standard/5183f151e4bb210219035808.png"}}, "comments": [{"body": "possible #lens right of centre top.", "user_id": "50736a07d10d2478c100261f", "tags": ["lens"], "created_at": "2013-12-23T10:28:02Z", "updated_at": "2013-12-23T10:28:02Z", "user_zooniverse_id": 833398, "mentions": [], "response_to": null, "upvotes": [], "_id": "52b81032996c9e7a4c000003", "user_name": "ChrisMolloy"}, {"body": "marked it as one - just in case. Can't help thinking it is a pseudo-ring / spiral galaxy.", "user_id": "50bf97bd56175a4982000d4e", "tags": [], "created_at": "2013-08-16T18:05:27Z", "updated_at": "2013-08-16T18:05:27Z", "user_zooniverse_id": 211122, "mentions": [], "response_to": null, "upvotes": [], "_id": "520e69e7e8472647f00000e1", "user_name": "Capella05"}, {"body": "model results for ASW0004p3c: Plausible http://mite.physik.uzh.ch/data/002127", "user_id": "5092a8529177d03baa001c09", "tags": [], "created_at": "2013-06-27T04:41:47Z", "updated_at": "2013-06-27T04:41:47Z", "user_zooniverse_id": 1124697, "mentions": ["ASW0004P3C"], "response_to": null, "upvotes": [], "_id": "51cbc28b39ea5339bc0000a4", "user_name": "JasonJason"}, {"body": "Marked as #lens", "user_id": "5092a8529177d03baa001c09", "tags": ["lens"], "created_at": "2013-06-27T04:25:17Z", "updated_at": "2013-06-27T04:25:17Z", "user_zooniverse_id": 1124697, "mentions": [], "response_to": null, "upvotes": [], "_id": "51cbbead39ea530d6f0000e4", "user_name": "JasonJason"}, {"body": "Likewise. Let the folks in the basement determine it. Looks interesting though.", "user_id": "505e0458ba40af6b790031ee", "tags": [], "created_at": "2013-06-15T19:06:59Z", "updated_at": "2013-06-15T19:06:59Z", "user_zooniverse_id": 2183, "mentions": [], "response_to": null, "upvotes": [], "_id": "51bcbb53501e7e1d1800003f", "user_name": "lamperti"}, {"body": "Looks nice, but could also be spiral arms. i would've marked it  just in case ! :-D\r\n", "user_id": "503e2b5eba40af242e000052", "tags": [], "created_at": "2013-06-10T18:57:05Z", "updated_at": "2013-06-10T18:57:05Z", "user_zooniverse_id": 137795, "mentions": [], "response_to": null, "upvotes": [], "_id": "51b6218139ea536de00003ad", "user_name": "ElisabethB"}, {"body": "Faint arc at one o'clock? ", "user_id": "518a6f7dcaaa1f295700000b", "tags": [], "created_at": "2013-06-10T18:44:26Z", "updated_at": "2013-06-10T18:44:26Z", "user_zooniverse_id": 1415327, "mentions": [], "response_to": null, "upvotes": [], "_id": "51b61e8ab9d58a1b0c000038", "user_name": "Stedman"}], "updated_at": "2013-12-23T10:28:02Z", "user_zooniverse_id": 1415327, "comments_count": 7, "board": {}, "last_comment": {"body": "possible #lens right of centre top.", "user_id": "50736a07d10d2478c100261f", "tags": ["lens"], "created_at": "2013-12-23T10:28:02Z", "updated_at": "2013-12-23T10:28:02Z", "user_zooniverse_id": 833398, "mentions": [], "response_to": null, "upvotes": [], "_id": "52b81032996c9e7a4c000003", "user_name": "ChrisMolloy"}, "project_id": "5101a1341a320ea77f000001", "user_name": "Stedman", "id": "51b61e8ab9d58a1b0c000039"}, "tags": [{"count": 2, "_id": "lens"}], "classification_count": 46, "created_at": "2013-05-30T15:49:47Z", "activated_at": "2013-12-10T16:29:18Z", "updated_at": "2013-12-23T10:28:03Z", "random": 0.3921292173753448, "state": "complete", "zooniverse_id": "ASW0004p3c", "workflow_ids": ["528107773ae7400fd4000001"], "location": {"thumbnail": "http://spacewarps.org/subjects/thumbnail/5183f151e4bb210219035808.png", "standard": "http://spacewarps.org/subjects/standard/5183f151e4bb210219035808.png"}, "mentions": [{"follower_ids": [], "zooniverse_id": "DSW000057v", "last_updated": "2013-12-23T10:28:02Z", "users": 5, "title": "ASW0004p3c", "focus": {"base_type": "Subject", "_id": "ASW0004p3c", "type": "SpacewarpSubject", "name": "ASW0004p3c", "location": {"thumbnail": "http://spacewarps.org/subjects/thumbnail/5183f151e4bb210219035808.png", "standard": "http://spacewarps.org/subjects/standard/5183f151e4bb210219035808.png"}}, "comments": 7}, {"board_id": "BSW0000006", "category": "science", "zooniverse_id": "DSW00004zu", "last_updated": "2014-01-08T18:31:38Z", "users": 7, "title": "Modelled Candidates 2013", "follower_ids": ["518a7d162887f31026000015", "5051f7e7ba40af0ca600122c"], "focus": {"_id": "BSW0000006", "type": "Board", "base_type": "Board", "name": "Modelling"}, "comments": 172, "board": "Modelling"}], "collections": [{"zooniverse_id": "CSWS000ftu", "user_id": "50508b810454e27a73002f60", "subjects_count": 1000, "title": "My Dashboard", "user_name": "seminatalia", "updated_at": "2014-01-11T18:06:50Z", "user_zooniverse_id": 207698, "subjects": [{"zooniverse_id": "ASW0000cnm", "location": {"thumbnail": "http://spacewarps.org/subjects/thumbnail/5183f151e4bb210219004012.png", "standard": "http://spacewarps.org/subjects/standard/5183f151e4bb210219004012.png"}}, {"zooniverse_id": "ASW0005t4d", "location": {"thumbnail": "http://spacewarps.org/subjects/thumbnail/5183f151e4bb2102190422ad.png", "standard": "http://spacewarps.org/subjects/standard/5183f151e4bb2102190422ad.png"}}, {"zooniverse_id": "ASW0003uzj", "location": {"thumbnail": "http://spacewarps.org/subjects/thumbnail/5183f151e4bb21021902bf9f.png", "standard": "http://spacewarps.org/subjects/standard/5183f151e4bb21021902bf9f.png"}}, {"zooniverse_id": "ASW0004nan", "location": {"thumbnail": "http://spacewarps.org/subjects/thumbnail/5183f151e4bb210219034eef.png", "standard": "http://spacewarps.org/subjects/standard/5183f151e4bb210219034eef.png"}}, {"zooniverse_id": "ASW00013qd", "location": {"thumbnail": "http://spacewarps.org/subjects/thumbnail/5183f151e4bb21021900c925.png", "standard": "http://spacewarps.org/subjects/standard/5183f151e4bb21021900c925.png"}}, {"zooniverse_id": "ASW0003mxs", "location": {"thumbnail": "http://spacewarps.org/subjects/thumbnail/5183f151e4bb2102190296e0.png", "standard": "http://spacewarps.org/subjects/standard/5183f151e4bb2102190296e0.png"}}, {"zooniverse_id": "ASW0009a69", "location": {"thumbnail": "http://spacewarps.org/subjects/thumbnail/5183f151e4bb210219069bc1.png", "standard": "http://spacewarps.org/subjects/standard/5183f151e4bb210219069bc1.png"}}, {"zooniverse_id": "ASW0003mdl", "location": {"thumbnail": "http://spacewarps.org/subjects/thumbnail/5183f151e4bb210219029409.png", "standard": "http://spacewarps.org/subjects/standard/5183f151e4bb210219029409.png"}}, {"zooniverse_id": "ASW000990c", "location": {"thumbnail": "http://spacewarps.org/subjects/thumbnail/5183f151e4bb2102190695dc.png", "standard": "http://spacewarps.org/subjects/standard/5183f151e4bb2102190695dc.png"}}, {"zooniverse_id": "ASW0005osc", "location": {"thumbnail": "http://spacewarps.org/subjects/thumbnail/5183f151e4bb210219040cbc.png", "standard": "http://spacewarps.org/subjects/standard/5183f151e4bb210219040cbc.png"}}], "project_id": "5101a1341a320ea77f000001", "type": "SubjectSet", "id": "519f8f5d643d13184d00000c", "description": "All Space Warp images examined in the Quick Dashboard."}, {"zooniverse_id": "CSWS000cqc", "user_id": "5052e158ba40af69f1003bd5", "subjects_count": 1000, "title": "My Candidates", "user_name": "Damon22", "updated_at": "2014-01-11T10:50:11Z", "user_zooniverse_id": 577440, "subjects": [{"zooniverse_id": "ASW0000kav", "location": {"thumbnail": "http://spacewarps.org/subjects/thumbnail/5183f151e4bb2102190066c7.png", "standard": "http://spacewarps.org/subjects/standard/5183f151e4bb2102190066c7.png"}}, {"zooniverse_id": "ASW00004ko", "location": {"thumbnail": "http://spacewarps.org/subjects/thumbnail/5183f151e4bb210219001728.png", "standard": "http://spacewarps.org/subjects/standard/5183f151e4bb210219001728.png"}}, {"zooniverse_id": "ASW0001goi", "location": {"thumbnail": "http://spacewarps.org/subjects/thumbnail/5183f151e4bb210219010ab2.png", "standard": "http://spacewarps.org/subjects/standard/5183f151e4bb210219010ab2.png"}}, {"zooniverse_id": "ASW0000g59", "location": {"thumbnail": "http://spacewarps.org/subjects/thumbnail/5183f151e4bb2102190051bd.png", "standard": "http://spacewarps.org/subjects/standard/5183f151e4bb2102190051bd.png"}}, {"zooniverse_id": "ASW00026ws", "location": {"thumbnail": "http://spacewarps.org/subjects/thumbnail/5183f151e4bb210219018f7c.png", "standard": "http://spacewarps.org/subjects/standard/5183f151e4bb210219018f7c.png"}}, {"zooniverse_id": "ASW0004w11", "location": {"thumbnail": "http://spacewarps.org/subjects/thumbnail/5183f151e4bb210219037b25.png", "standard": "http://spacewarps.org/subjects/standard/5183f151e4bb210219037b25.png"}}, {"zooniverse_id": "ASW000301l", "location": {"thumbnail": "http://spacewarps.org/subjects/thumbnail/5183f151e4bb2102190222f9.png", "standard": "http://spacewarps.org/subjects/standard/5183f151e4bb2102190222f9.png"}}, {"zooniverse_id": "ASW0002bpo", "location": {"thumbnail": "http://spacewarps.org/subjects/thumbnail/5183f151e4bb21021901a7cc.png", "standard": "http://spacewarps.org/subjects/standard/5183f151e4bb21021901a7cc.png"}}, {"zooniverse_id": "ASW00000qa", "location": {"thumbnail": "http://spacewarps.org/subjects/thumbnail/5183f151e4bb2102190003b2.png", "standard": "http://spacewarps.org/subjects/standard/5183f151e4bb2102190003b2.png"}}, {"zooniverse_id": "ASW000355x", "location": {"thumbnail": "http://spacewarps.org/subjects/thumbnail/5183f151e4bb210219023ce5.png", "standard": "http://spacewarps.org/subjects/standard/5183f151e4bb210219023ce5.png"}}], "project_id": "5101a1341a320ea77f000001", "type": "SubjectSet", "id": "518ef36c60f4364b8e000015", "description": "Gravitational lens candidates."}, {"zooniverse_id": "CSWS0000y9", "user_id": "50ed9f6960d4054a82000023", "subjects_count": 237, "title": "My Dashboard", "user_name": "doug67", "updated_at": "2014-01-10T20:50:21Z", "user_zooniverse_id": 1098473, "subjects": [{"zooniverse_id": "ASW0000a7l", "location": {"thumbnail": "http://spacewarps.org/subjects/thumbnail/5183f151e4bb2102190033b1.png", "standard": "http://spacewarps.org/subjects/standard/5183f151e4bb2102190033b1.png"}}, {"zooniverse_id": "ASW0000p27", "location": {"thumbnail": "http://spacewarps.org/subjects/thumbnail/5183f151e4bb210219007edf.png", "standard": "http://spacewarps.org/subjects/standard/5183f151e4bb210219007edf.png"}}, {"zooniverse_id": "ASW0000p03", "location": {"thumbnail": "http://spacewarps.org/subjects/thumbnail/5183f151e4bb210219007e93.png", "standard": "http://spacewarps.org/subjects/standard/5183f151e4bb210219007e93.png"}}, {"zooniverse_id": "ASW00007ok", "location": {"thumbnail": "http://spacewarps.org/subjects/thumbnail/5183f151e4bb2102190026e4.png", "standard": "http://spacewarps.org/subjects/standard/5183f151e4bb2102190026e4.png"}}, {"zooniverse_id": "ASW0000cqg", "location": {"thumbnail": "http://spacewarps.org/subjects/thumbnail/5183f151e4bb210219004078.png", "standard": "http://spacewarps.org/subjects/standard/5183f151e4bb210219004078.png"}}, {"zooniverse_id": "ASW0000sba", "location": {"thumbnail": "http://spacewarps.org/subjects/thumbnail/5183f151e4bb210219008f56.png", "standard": "http://spacewarps.org/subjects/standard/5183f151e4bb210219008f56.png"}}, {"zooniverse_id": "ASW00001g7", "location": {"thumbnail": "http://spacewarps.org/subjects/thumbnail/5183f151e4bb210219000757.png", "standard": "http://spacewarps.org/subjects/standard/5183f151e4bb210219000757.png"}}, {"zooniverse_id": "ASW0000vus", "location": {"thumbnail": "http://spacewarps.org/subjects/thumbnail/5183f151e4bb21021900a144.png", "standard": "http://spacewarps.org/subjects/standard/5183f151e4bb21021900a144.png"}}, {"zooniverse_id": "ASW00006e0", "location": {"thumbnail": "http://spacewarps.org/subjects/thumbnail/5183f151e4bb210219002058.png", "standard": "http://spacewarps.org/subjects/standard/5183f151e4bb210219002058.png"}}, {"zooniverse_id": "ASW0000gx3", "location": {"thumbnail": "http://spacewarps.org/subjects/thumbnail/5183f151e4bb2102190055a7.png", "standard": "http://spacewarps.org/subjects/standard/5183f151e4bb2102190055a7.png"}}], "project_id": "5101a1341a320ea77f000001", "type": "SubjectSet", "id": "518a788e2887f30af3000014", "description": "All Space Warp images examined in the Quick Dashboard."}, {"zooniverse_id": "CSWS0000a6", "user_id": "5041e7950454e2792f00010a", "subjects_count": 1000, "title": "My Dashboard", "user_name": "kiske1", "updated_at": "2014-01-10T16:06:39Z", "user_zooniverse_id": 274343, "subjects": [{"zooniverse_id": "ASW0009dff", "location": {"thumbnail": "http://spacewarps.org/subjects/thumbnail/5183f151e4bb2102190132d0.png", "standard": "http://spacewarps.org/subjects/standard/5183f151e4bb2102190132d0.png"}}, {"zooniverse_id": "ASW00098f6", "location": {"thumbnail": "http://spacewarps.org/subjects/thumbnail/5183f151e4bb2102190692e2.png", "standard": "http://spacewarps.org/subjects/standard/5183f151e4bb2102190692e2.png"}}, {"zooniverse_id": "ASW0009dgg", "location": {"thumbnail": "http://spacewarps.org/subjects/thumbnail/5183f151e4bb21021901f17c.png", "standard": "http://spacewarps.org/subjects/standard/5183f151e4bb21021901f17c.png"}}, {"zooniverse_id": "ASW00023e3", "location": {"thumbnail": "http://spacewarps.org/subjects/thumbnail/5183f151e4bb210219017dab.png", "standard": "http://spacewarps.org/subjects/standard/5183f151e4bb210219017dab.png"}}, {"zooniverse_id": "ASW0005i7o", "location": {"thumbnail": "http://spacewarps.org/subjects/thumbnail/5183f151e4bb21021903eb74.png", "standard": "http://spacewarps.org/subjects/standard/5183f151e4bb21021903eb74.png"}}, {"zooniverse_id": "ASW00005hl", "location": {"thumbnail": "http://spacewarps.org/subjects/thumbnail/5183f151e4bb210219001bc9.png", "standard": "http://spacewarps.org/subjects/standard/5183f151e4bb210219001bc9.png"}}, {"zooniverse_id": "ASW0009dij", "location": {"thumbnail": "http://spacewarps.org/subjects/thumbnail/5183f151e4bb2102190023f9.png", "standard": "http://spacewarps.org/subjects/standard/5183f151e4bb2102190023f9.png"}}, {"zooniverse_id": "ASW00038gl", "location": {"thumbnail": "http://spacewarps.org/subjects/thumbnail/5183f151e4bb210219024d95.png", "standard": "http://spacewarps.org/subjects/standard/5183f151e4bb210219024d95.png"}}, {"zooniverse_id": "ASW00091ub", "location": {"thumbnail": "http://spacewarps.org/subjects/thumbnail/5183f151e4bb210219067193.png", "standard": "http://spacewarps.org/subjects/standard/5183f151e4bb210219067193.png"}}, {"zooniverse_id": "ASW0007oeq", "location": {"thumbnail": "http://spacewarps.org/subjects/thumbnail/5183f151e4bb210219057752.png", "standard": "http://spacewarps.org/subjects/standard/5183f151e4bb210219057752.png"}}], "project_id": "5101a1341a320ea77f000001", "type": "SubjectSet", "id": "518a4a07de59d95395000008", "description": "All Space Warp images examined in the Quick Dashboard."}, {"zooniverse_id": "CSWS0000a7", "user_id": "5041e7950454e2792f00010a", "subjects_count": 799, "title": "My Candidates", "user_name": "kiske1", "updated_at": "2014-01-10T13:58:18Z", "user_zooniverse_id": 274343, "subjects": [{"zooniverse_id": "ASW0000a7l", "location": {"thumbnail": "http://spacewarps.org/subjects/thumbnail/5183f151e4bb2102190033b1.png", "standard": "http://spacewarps.org/subjects/standard/5183f151e4bb2102190033b1.png"}}, {"zooniverse_id": "ASW0000p35", "location": {"thumbnail": "http://spacewarps.org/subjects/thumbnail/5183f151e4bb210219007f01.png", "standard": "http://spacewarps.org/subjects/standard/5183f151e4bb210219007f01.png"}}, {"zooniverse_id": "ASW0000nzf", "location": {"thumbnail": "http://spacewarps.org/subjects/thumbnail/5183f151e4bb21021900796b.png", "standard": "http://spacewarps.org/subjects/standard/5183f151e4bb21021900796b.png"}}, {"zooniverse_id": "ASW0000op3", "location": {"thumbnail": "http://spacewarps.org/subjects/thumbnail/5183f151e4bb210219007d07.png", "standard": "http://spacewarps.org/subjects/standard/5183f151e4bb210219007d07.png"}}, {"zooniverse_id": "ASW0001sv5", "location": {"thumbnail": "http://spacewarps.org/subjects/thumbnail/5183f151e4bb210219014861.png", "standard": "http://spacewarps.org/subjects/standard/5183f151e4bb210219014861.png"}}, {"zooniverse_id": "ASW0000ug0", "location": {"thumbnail": "http://spacewarps.org/subjects/thumbnail/5183f151e4bb210219009a20.png", "standard": "http://spacewarps.org/subjects/standard/5183f151e4bb210219009a20.png"}}, {"zooniverse_id": "ASW0000p6q", "location": {"thumbnail": "http://spacewarps.org/subjects/thumbnail/5183f151e4bb210219007f82.png", "standard": "http://spacewarps.org/subjects/standard/5183f151e4bb210219007f82.png"}}, {"zooniverse_id": "ASW0001l0z", "location": {"thumbnail": "http://spacewarps.org/subjects/thumbnail/5183f151e4bb2102190120b3.png", "standard": "http://spacewarps.org/subjects/standard/5183f151e4bb2102190120b3.png"}}, {"zooniverse_id": "ASW0000da7", "location": {"thumbnail": "http://spacewarps.org/subjects/thumbnail/5183f151e4bb21021900433f.png", "standard": "http://spacewarps.org/subjects/standard/5183f151e4bb21021900433f.png"}}, {"zooniverse_id": "ASW0001mlm", "location": {"thumbnail": "http://spacewarps.org/subjects/thumbnail/5183f151e4bb2102190128aa.png", "standard": "http://spacewarps.org/subjects/standard/5183f151e4bb2102190128aa.png"}}], "project_id": "5101a1341a320ea77f000001", "type": "SubjectSet", "id": "518a4a0bcaaa1f1be6000004", "description": "Gravitational lens candidates."}, {"zooniverse_id": "CSWS0001rh", "user_id": "50bf97bd56175a4982000d4e", "subjects_count": 454, "title": "My Candidates", "user_name": "Capella05", "updated_at": "2014-01-10T13:25:11Z", "user_zooniverse_id": 211122, "subjects": [{"zooniverse_id": "ASW00005mq", "location": {"thumbnail": "http://spacewarps.org/subjects/thumbnail/5183f151e4bb210219001c82.png", "standard": "http://spacewarps.org/subjects/standard/5183f151e4bb210219001c82.png"}}, {"zooniverse_id": "ASW00000x0", "location": {"thumbnail": "http://spacewarps.org/subjects/thumbnail/5183f151e4bb2102190004a4.png", "standard": "http://spacewarps.org/subjects/standard/5183f151e4bb2102190004a4.png"}}, {"zooniverse_id": "ASW0000eee", "location": {"thumbnail": "http://spacewarps.org/subjects/thumbnail/5183f151e4bb2102190048e6.png", "standard": "http://spacewarps.org/subjects/standard/5183f151e4bb2102190048e6.png"}}, {"zooniverse_id": "ASW0000xjl", "location": {"thumbnail": "http://spacewarps.org/subjects/thumbnail/5183f151e4bb21021900a9d1.png", "standard": "http://spacewarps.org/subjects/standard/5183f151e4bb21021900a9d1.png"}}, {"zooniverse_id": "ASW00005u6", "location": {"thumbnail": "http://spacewarps.org/subjects/thumbnail/5183f151e4bb210219001d8e.png", "standard": "http://spacewarps.org/subjects/standard/5183f151e4bb210219001d8e.png"}}, {"zooniverse_id": "ASW00013mp", "location": {"thumbnail": "http://spacewarps.org/subjects/thumbnail/5183f151e4bb21021900c8a1.png", "standard": "http://spacewarps.org/subjects/standard/5183f151e4bb21021900c8a1.png"}}, {"zooniverse_id": "ASW0000d82", "location": {"thumbnail": "http://spacewarps.org/subjects/thumbnail/5183f151e4bb2102190042f2.png", "standard": "http://spacewarps.org/subjects/standard/5183f151e4bb2102190042f2.png"}}, {"zooniverse_id": "ASW0001q3u", "location": {"thumbnail": "http://spacewarps.org/subjects/thumbnail/5183f151e4bb210219013a6a.png", "standard": "http://spacewarps.org/subjects/standard/5183f151e4bb210219013a6a.png"}}, {"zooniverse_id": "ASW0000scs", "location": {"thumbnail": "http://spacewarps.org/subjects/thumbnail/5183f151e4bb210219008f8c.png", "standard": "http://spacewarps.org/subjects/standard/5183f151e4bb210219008f8c.png"}}, {"zooniverse_id": "ASW0000us6", "location": {"thumbnail": "http://spacewarps.org/subjects/thumbnail/5183f151e4bb210219009bd6.png", "standard": "http://spacewarps.org/subjects/standard/5183f151e4bb210219009bd6.png"}}], "project_id": "5101a1341a320ea77f000001", "type": "SubjectSet", "id": "518a7fa1de59d97268000004", "description": "Gravitational lens candidates."}, {"zooniverse_id": "CSWS000kpz", "user_id": "51682edbc237d924550000fd", "subjects_count": 1000, "title": "My Dashboard", "user_name": "lemisiak", "updated_at": "2014-01-10T11:22:35Z", "user_zooniverse_id": 1361364, "subjects": [{"zooniverse_id": "ASW0004knk", "location": {"thumbnail": "http://spacewarps.org/subjects/thumbnail/5183f151e4bb210219034190.png", "standard": "http://spacewarps.org/subjects/standard/5183f151e4bb210219034190.png"}}, {"zooniverse_id": "ASW0003zdh", "location": {"thumbnail": "http://spacewarps.org/subjects/thumbnail/5183f151e4bb21021902d5d5.png", "standard": "http://spacewarps.org/subjects/standard/5183f151e4bb21021902d5d5.png"}}, {"zooniverse_id": "ASW0004gdx", "location": {"thumbnail": "http://spacewarps.org/subjects/thumbnail/5183f151e4bb210219032bf5.png", "standard": "http://spacewarps.org/subjects/standard/5183f151e4bb210219032bf5.png"}}, {"zooniverse_id": "ASW0006pb9", "location": {"thumbnail": "http://spacewarps.org/subjects/thumbnail/5183f151e4bb21021904c5a5.png", "standard": "http://spacewarps.org/subjects/standard/5183f151e4bb21021904c5a5.png"}}, {"zooniverse_id": "ASW0005v7s", "location": {"thumbnail": "http://spacewarps.org/subjects/thumbnail/5183f151e4bb210219042d48.png", "standard": "http://spacewarps.org/subjects/standard/5183f151e4bb210219042d48.png"}}, {"zooniverse_id": "ASW0000wrl", "location": {"thumbnail": "http://spacewarps.org/subjects/thumbnail/5183f151e4bb21021900a5e1.png", "standard": "http://spacewarps.org/subjects/standard/5183f151e4bb21021900a5e1.png"}}, {"zooniverse_id": "ASW0003ft1", "location": {"thumbnail": "http://spacewarps.org/subjects/thumbnail/5183f151e4bb2102190272c5.png", "standard": "http://spacewarps.org/subjects/standard/5183f151e4bb2102190272c5.png"}}, {"zooniverse_id": "ASW0007cfq", "location": {"thumbnail": "http://spacewarps.org/subjects/thumbnail/5183f151e4bb210219053ab6.png", "standard": "http://spacewarps.org/subjects/standard/5183f151e4bb210219053ab6.png"}}, {"zooniverse_id": "ASW0004jxj", "location": {"thumbnail": "http://spacewarps.org/subjects/thumbnail/5183f151e4bb210219033de7.png", "standard": "http://spacewarps.org/subjects/standard/5183f151e4bb210219033de7.png"}}, {"zooniverse_id": "ASW0006jp5", "location": {"thumbnail": "http://spacewarps.org/subjects/thumbnail/5183f151e4bb21021904a939.png", "standard": "http://spacewarps.org/subjects/standard/5183f151e4bb21021904a939.png"}}], "project_id": "5101a1341a320ea77f000001", "type": "SubjectSet", "id": "51d6a30839ea53530500018b", "description": "All Space Warp images examined in the Quick Dashboard."}, {"zooniverse_id": "CSWS000kq0", "user_id": "51682edbc237d924550000fd", "subjects_count": 665, "title": "My Candidates", "user_name": "lemisiak", "updated_at": "2014-01-10T11:07:15Z", "user_zooniverse_id": 1361364, "subjects": [{"zooniverse_id": "ASW0000a7l", "location": {"thumbnail": "http://spacewarps.org/subjects/thumbnail/5183f151e4bb2102190033b1.png", "standard": "http://spacewarps.org/subjects/standard/5183f151e4bb2102190033b1.png"}}, {"zooniverse_id": "ASW0000bsh", "location": {"thumbnail": "http://spacewarps.org/subjects/thumbnail/5183f151e4bb210219003bb1.png", "standard": "http://spacewarps.org/subjects/standard/5183f151e4bb210219003bb1.png"}}, {"zooniverse_id": "ASW0002uny", "location": {"thumbnail": "http://spacewarps.org/subjects/thumbnail/5183f151e4bb2102190207be.png", "standard": "http://spacewarps.org/subjects/standard/5183f151e4bb2102190207be.png"}}, {"zooniverse_id": "ASW0000rz4", "location": {"thumbnail": "http://spacewarps.org/subjects/thumbnail/5183f151e4bb210219008da0.png", "standard": "http://spacewarps.org/subjects/standard/5183f151e4bb210219008da0.png"}}, {"zooniverse_id": "ASW0003n42", "location": {"thumbnail": "http://spacewarps.org/subjects/thumbnail/5183f151e4bb2102190297c2.png", "standard": "http://spacewarps.org/subjects/standard/5183f151e4bb2102190297c2.png"}}, {"zooniverse_id": "ASW000065n", "location": {"thumbnail": "http://spacewarps.org/subjects/thumbnail/5183f151e4bb210219001f2b.png", "standard": "http://spacewarps.org/subjects/standard/5183f151e4bb210219001f2b.png"}}, {"zooniverse_id": "ASW0000g54", "location": {"thumbnail": "http://spacewarps.org/subjects/thumbnail/5183f151e4bb2102190051b8.png", "standard": "http://spacewarps.org/subjects/standard/5183f151e4bb2102190051b8.png"}}, {"zooniverse_id": "ASW000545b", "location": {"thumbnail": "http://spacewarps.org/subjects/thumbnail/5183f151e4bb21021903a43f.png", "standard": "http://spacewarps.org/subjects/standard/5183f151e4bb21021903a43f.png"}}, {"zooniverse_id": "ASW0000v7g", "location": {"thumbnail": "http://spacewarps.org/subjects/thumbnail/5183f151e4bb210219009dfc.png", "standard": "http://spacewarps.org/subjects/standard/5183f151e4bb210219009dfc.png"}}, {"zooniverse_id": "ASW0000vub", "location": {"thumbnail": "http://spacewarps.org/subjects/thumbnail/5183f151e4bb21021900a133.png", "standard": "http://spacewarps.org/subjects/standard/5183f151e4bb21021900a133.png"}}], "project_id": "5101a1341a320ea77f000001", "type": "SubjectSet", "id": "51d6a38bf6ad777ed300003c", "description": "Gravitational lens candidates."}, {"zooniverse_id": "CSWS000hgl", "user_id": "518fca0860f436096a000009", "subjects_count": 704, "title": "My Candidates", "user_name": "chaoticidealism", "updated_at": "2014-01-10T04:04:02Z", "user_zooniverse_id": 1422640, "subjects": [{"zooniverse_id": "ASW0000a7l", "location": {"thumbnail": "http://spacewarps.org/subjects/thumbnail/5183f151e4bb2102190033b1.png", "standard": "http://spacewarps.org/subjects/standard/5183f151e4bb2102190033b1.png"}}, {"zooniverse_id": "ASW0000bsh", "location": {"thumbnail": "http://spacewarps.org/subjects/thumbnail/5183f151e4bb210219003bb1.png", "standard": "http://spacewarps.org/subjects/standard/5183f151e4bb210219003bb1.png"}}, {"zooniverse_id": "ASW0002pjb", "location": {"thumbnail": "http://spacewarps.org/subjects/thumbnail/5183f151e4bb21021901edc7.png", "standard": "http://spacewarps.org/subjects/standard/5183f151e4bb21021901edc7.png"}}, {"zooniverse_id": "ASW000124z", "location": {"thumbnail": "http://spacewarps.org/subjects/thumbnail/5183f151e4bb21021900c113.png", "standard": "http://spacewarps.org/subjects/standard/5183f151e4bb21021900c113.png"}}, {"zooniverse_id": "ASW0000rdb", "location": {"thumbnail": "http://spacewarps.org/subjects/thumbnail/5183f151e4bb210219008a8f.png", "standard": "http://spacewarps.org/subjects/standard/5183f151e4bb210219008a8f.png"}}, {"zooniverse_id": "ASW0000dn4", "location": {"thumbnail": "http://spacewarps.org/subjects/thumbnail/5183f151e4bb210219004510.png", "standard": "http://spacewarps.org/subjects/standard/5183f151e4bb210219004510.png"}}, {"zooniverse_id": "ASW0003ln8", "location": {"thumbnail": "http://spacewarps.org/subjects/thumbnail/5183f151e4bb210219029054.png", "standard": "http://spacewarps.org/subjects/standard/5183f151e4bb210219029054.png"}}, {"zooniverse_id": "ASW0002jwl", "location": {"thumbnail": "http://spacewarps.org/subjects/thumbnail/5183f151e4bb21021901d145.png", "standard": "http://spacewarps.org/subjects/standard/5183f151e4bb21021901d145.png"}}, {"zooniverse_id": "ASW0001ohy", "location": {"thumbnail": "http://spacewarps.org/subjects/thumbnail/5183f151e4bb210219013246.png", "standard": "http://spacewarps.org/subjects/standard/5183f151e4bb210219013246.png"}}, {"zooniverse_id": "ASW0001ssm", "location": {"thumbnail": "http://spacewarps.org/subjects/thumbnail/5183f151e4bb210219014806.png", "standard": "http://spacewarps.org/subjects/standard/5183f151e4bb210219014806.png"}}], "project_id": "5101a1341a320ea77f000001", "type": "SubjectSet", "id": "51a55d24a507e81e3900003b", "description": "Gravitational lens candidates."}, {"zooniverse_id": "CSWS0001ra", "user_id": "503e5550ba40af242000020c", "subjects_count": 1000, "title": "My Dashboard", "user_name": "dennispattensr", "updated_at": "2014-01-10T03:45:15Z", "user_zooniverse_id": 599716, "subjects": [{"zooniverse_id": "ASW0000foh", "location": {"thumbnail": "http://spacewarps.org/subjects/thumbnail/5183f151e4bb210219004f61.png", "standard": "http://spacewarps.org/subjects/standard/5183f151e4bb210219004f61.png"}}, {"zooniverse_id": "ASW0001f0g", "location": {"thumbnail": "http://spacewarps.org/subjects/thumbnail/5183f151e4bb210219010240.png", "standard": "http://spacewarps.org/subjects/standard/5183f151e4bb210219010240.png"}}, {"zooniverse_id": "ASW0000ohe", "location": {"thumbnail": "http://spacewarps.org/subjects/thumbnail/5183f151e4bb210219007bf2.png", "standard": "http://spacewarps.org/subjects/standard/5183f151e4bb210219007bf2.png"}}, {"zooniverse_id": "ASW00005ma", "location": {"thumbnail": "http://spacewarps.org/subjects/thumbnail/5183f151e4bb210219001c72.png", "standard": "http://spacewarps.org/subjects/standard/5183f151e4bb210219001c72.png"}}, {"zooniverse_id": "ASW0005hgm", "location": {"thumbnail": "http://spacewarps.org/subjects/thumbnail/5183f151e4bb21021903e7a6.png", "standard": "http://spacewarps.org/subjects/standard/5183f151e4bb21021903e7a6.png"}}, {"zooniverse_id": "ASW0000ueh", "location": {"thumbnail": "http://spacewarps.org/subjects/thumbnail/5183f151e4bb2102190099e9.png", "standard": "http://spacewarps.org/subjects/standard/5183f151e4bb2102190099e9.png"}}, {"zooniverse_id": "ASW0000vgi", "location": {"thumbnail": "http://spacewarps.org/subjects/thumbnail/5183f151e4bb210219009f42.png", "standard": "http://spacewarps.org/subjects/standard/5183f151e4bb210219009f42.png"}}, {"zooniverse_id": "ASW0000u7v", "location": {"thumbnail": "http://spacewarps.org/subjects/thumbnail/5183f151e4bb2102190098fb.png", "standard": "http://spacewarps.org/subjects/standard/5183f151e4bb2102190098fb.png"}}, {"zooniverse_id": "ASW0006yn1", "location": {"thumbnail": "http://spacewarps.org/subjects/thumbnail/5183f151e4bb21021904f4dd.png", "standard": "http://spacewarps.org/subjects/standard/5183f151e4bb21021904f4dd.png"}}, {"zooniverse_id": "ASW00005re", "location": {"thumbnail": "http://spacewarps.org/subjects/thumbnail/5183f151e4bb210219001d2a.png", "standard": "http://spacewarps.org/subjects/standard/5183f151e4bb210219001d2a.png"}}], "project_id": "5101a1341a320ea77f000001", "type": "SubjectSet", "id": "518a7f99de59d97268000003", "description": "All Space Warp images examined in the Quick Dashboard."}], "group_id": "5154a3783ae74086ab000001", "board_discussions": {"science": [], "help": [], "chat": []}, "id": "5183f151e4bb210219035808", "metadata": {"data_set": "D6", "stage2": true, "id": "CFHTLS_077_0880", "stage_1_classification_count": 50}}